setup.py
pweather.egg-info/PKG-INFO
pweather.egg-info/SOURCES.txt
pweather.egg-info/dependency_links.txt
pweather.egg-info/entry_points.txt
pweather.egg-info/not-zip-safe
pweather.egg-info/requires.txt
pweather.egg-info/top_level.txt
src/__init__.py
src/pweather.py