Metadata-Version: 1.0
Name: pweather
Version: 0.1.1
Summary: 直接在终端查城市天气情况
Home-page: https://github.com/laozhaokun/pweather
Author: zhaohf
Author-email: zhaohuafei@gmail.com
License: UNKNOWN
Keywords: python weather report terminal
Platform: UNKNOWN
